<?xml version="1.0" encoding="utf-8"?>
<Document>
  <Engineering version="V20" />
  <SW.Blocks.FB ID="0">
    <AttributeList>
      <AutoNumber>false</AutoNumber>
      <Interface><Sections xmlns="http://www.siemens.com/automation/Openness/SW/Interface/v5">
  <Section Name="Input">
    <Member Name="Req_arms_move_to_workPos" Datatype="Bool" />
    <Member Name="Req_arms_move_to_basePos" Datatype="Bool" />
    <Member Name="BasePos1" Datatype="Bool" />
    <Member Name="WorkPos1" Datatype="Bool" />
    <Member Name="BasePos2" Datatype="Bool" />
    <Member Name="WorkPos2" Datatype="Bool" />
    <Member Name="Palette_on_station" Datatype="Bool" />
    <Member Name="Arms_in_pos" Datatype="Bool" />
    <Member Name="Hydraulic_unit_rdy" Datatype="Bool" />
  </Section>
  <Section Name="Output">
    <Member Name="MoveToWorkPos" Datatype="Bool" />
    <Member Name="MoveToBasePos" Datatype="Bool" />
  </Section>
  <Section Name="InOut" />
  <Section Name="Static">
    <Member Name="Alarm_Clamp_Not_Close_Properly" Datatype="TON_TIME" Version="1.0">
      <AttributeList>
        <BooleanAttribute Name="SetPoint" SystemDefined="true">true</BooleanAttribute>
      </AttributeList>
    </Member>
    <Member Name="Alarm_Clamp_Not_Open_Properly" Datatype="TON_TIME" Version="1.0">
      <AttributeList>
        <BooleanAttribute Name="SetPoint" SystemDefined="true">true</BooleanAttribute>
      </AttributeList>
    </Member>
  </Section>
  <Section Name="Temp" />
  <Section Name="Constant" />
</Sections></Interface>
      <MemoryLayout>Optimized</MemoryLayout>
      <MemoryReserve>100</MemoryReserve>
      <Name>Clamp</Name>
      <Namespace />
      <Number>431</Number>
      <ProgrammingLanguage>LAD</ProgrammingLanguage>
      <SetENOAutomatically>false</SetENOAutomatically>
    </AttributeList>
    <ObjectList>
      <MultilingualText ID="1" CompositionName="Comment">
        <ObjectList>
          <MultilingualTextItem ID="2" CompositionName="Items">
            <AttributeList>
              <Culture>en-US</Culture>
              <Text />
            </AttributeList>
          </MultilingualTextItem>
        </ObjectList>
      </MultilingualText>
      <SW.Blocks.CompileUnit ID="3" CompositionName="CompileUnits">
        <AttributeList>
          <NetworkSource><FlgNet xmlns="http://www.siemens.com/automation/Openness/SW/NetworkSource/FlgNet/v5">
  <Parts>
    <Access Scope="LocalVariable" UId="21">
      <Symbol>
        <Component Name="Req_arms_move_to_basePos" />
      </Symbol>
    </Access>
    <Access Scope="LocalVariable" UId="22">
      <Symbol>
        <Component Name="MoveToWorkPos" />
      </Symbol>
    </Access>
    <Access Scope="LocalVariable" UId="23">
      <Symbol>
        <Component Name="Arms_in_pos" />
      </Symbol>
    </Access>
    <Access Scope="LocalVariable" UId="24">
      <Symbol>
        <Component Name="BasePos1" />
      </Symbol>
    </Access>
    <Access Scope="LocalVariable" UId="25">
      <Symbol>
        <Component Name="BasePos2" />
      </Symbol>
    </Access>
    <Access Scope="LocalVariable" UId="26">
      <Symbol>
        <Component Name="MoveToBasePos" />
      </Symbol>
    </Access>
    <Part Name="Contact" UId="27" />
    <Part Name="Contact" UId="28">
      <Negated Name="operand" />
    </Part>
    <Part Name="Contact" UId="29" />
    <Part Name="Contact" UId="30">
      <Negated Name="operand" />
    </Part>
    <Part Name="Contact" UId="31">
      <Negated Name="operand" />
    </Part>
    <Part Name="O" UId="32">
      <TemplateValue Name="Card" Type="Cardinality">2</TemplateValue>
    </Part>
    <Part Name="Coil" UId="33" />
  </Parts>
  <Wires>
    <Wire UId="34">
      <Powerrail />
      <NameCon UId="27" Name="in" />
    </Wire>
    <Wire UId="35">
      <IdentCon UId="21" />
      <NameCon UId="27" Name="operand" />
    </Wire>
    <Wire UId="36">
      <NameCon UId="27" Name="out" />
      <NameCon UId="28" Name="in" />
    </Wire>
    <Wire UId="37">
      <IdentCon UId="22" />
      <NameCon UId="28" Name="operand" />
    </Wire>
    <Wire UId="38">
      <NameCon UId="28" Name="out" />
      <NameCon UId="29" Name="in" />
    </Wire>
    <Wire UId="39">
      <IdentCon UId="23" />
      <NameCon UId="29" Name="operand" />
    </Wire>
    <Wire UId="40">
      <NameCon UId="29" Name="out" />
      <NameCon UId="30" Name="in" />
      <NameCon UId="31" Name="in" />
    </Wire>
    <Wire UId="41">
      <IdentCon UId="24" />
      <NameCon UId="30" Name="operand" />
    </Wire>
    <Wire UId="42">
      <NameCon UId="30" Name="out" />
      <NameCon UId="32" Name="in1" />
    </Wire>
    <Wire UId="43">
      <IdentCon UId="25" />
      <NameCon UId="31" Name="operand" />
    </Wire>
    <Wire UId="44">
      <NameCon UId="31" Name="out" />
      <NameCon UId="32" Name="in2" />
    </Wire>
    <Wire UId="45">
      <NameCon UId="32" Name="out" />
      <NameCon UId="33" Name="in" />
    </Wire>
    <Wire UId="46">
      <IdentCon UId="26" />
      <NameCon UId="33" Name="operand" />
    </Wire>
  </Wires>
</FlgNet></NetworkSource>
          <ProgrammingLanguage>LAD</ProgrammingLanguage>
        </AttributeList>
        <ObjectList>
          <MultilingualText ID="4" CompositionName="Comment">
            <ObjectList>
              <MultilingualTextItem ID="5" CompositionName="Items">
                <AttributeList>
                  <Culture>en-US</Culture>
                  <Text />
                </AttributeList>
              </MultilingualTextItem>
            </ObjectList>
          </MultilingualText>
          <MultilingualText ID="6" CompositionName="Title">
            <ObjectList>
              <MultilingualTextItem ID="7" CompositionName="Items">
                <AttributeList>
                  <Culture>en-US</Culture>
                  <Text>Open Clamps</Text>
                </AttributeList>
              </MultilingualTextItem>
            </ObjectList>
          </MultilingualText>
        </ObjectList>
      </SW.Blocks.CompileUnit>
      <SW.Blocks.CompileUnit ID="8" CompositionName="CompileUnits">
        <AttributeList>
          <NetworkSource><FlgNet xmlns="http://www.siemens.com/automation/Openness/SW/NetworkSource/FlgNet/v5">
  <Parts>
    <Access Scope="LocalVariable" UId="21">
      <Symbol>
        <Component Name="Req_arms_move_to_workPos" />
      </Symbol>
    </Access>
    <Access Scope="LocalVariable" UId="22">
      <Symbol>
        <Component Name="MoveToBasePos" />
      </Symbol>
    </Access>
    <Access Scope="LocalVariable" UId="23">
      <Symbol>
        <Component Name="WorkPos1" />
      </Symbol>
    </Access>
    <Access Scope="LocalVariable" UId="24">
      <Symbol>
        <Component Name="WorkPos2" />
      </Symbol>
    </Access>
    <Access Scope="LocalVariable" UId="25">
      <Symbol>
        <Component Name="MoveToWorkPos" />
      </Symbol>
    </Access>
    <Part Name="Contact" UId="26" />
    <Part Name="Contact" UId="27">
      <Negated Name="operand" />
    </Part>
    <Part Name="Contact" UId="28">
      <Negated Name="operand" />
    </Part>
    <Part Name="Contact" UId="29">
      <Negated Name="operand" />
    </Part>
    <Part Name="O" UId="30">
      <TemplateValue Name="Card" Type="Cardinality">2</TemplateValue>
    </Part>
    <Part Name="Coil" UId="31" />
  </Parts>
  <Wires>
    <Wire UId="32">
      <Powerrail />
      <NameCon UId="26" Name="in" />
    </Wire>
    <Wire UId="33">
      <IdentCon UId="21" />
      <NameCon UId="26" Name="operand" />
    </Wire>
    <Wire UId="34">
      <NameCon UId="26" Name="out" />
      <NameCon UId="27" Name="in" />
    </Wire>
    <Wire UId="35">
      <IdentCon UId="22" />
      <NameCon UId="27" Name="operand" />
    </Wire>
    <Wire UId="36">
      <NameCon UId="27" Name="out" />
      <NameCon UId="28" Name="in" />
      <NameCon UId="29" Name="in" />
    </Wire>
    <Wire UId="37">
      <IdentCon UId="23" />
      <NameCon UId="28" Name="operand" />
    </Wire>
    <Wire UId="38">
      <NameCon UId="28" Name="out" />
      <NameCon UId="30" Name="in1" />
    </Wire>
    <Wire UId="39">
      <IdentCon UId="24" />
      <NameCon UId="29" Name="operand" />
    </Wire>
    <Wire UId="40">
      <NameCon UId="29" Name="out" />
      <NameCon UId="30" Name="in2" />
    </Wire>
    <Wire UId="41">
      <NameCon UId="30" Name="out" />
      <NameCon UId="31" Name="in" />
    </Wire>
    <Wire UId="42">
      <IdentCon UId="25" />
      <NameCon UId="31" Name="operand" />
    </Wire>
  </Wires>
</FlgNet></NetworkSource>
          <ProgrammingLanguage>LAD</ProgrammingLanguage>
        </AttributeList>
        <ObjectList>
          <MultilingualText ID="9" CompositionName="Comment">
            <ObjectList>
              <MultilingualTextItem ID="A" CompositionName="Items">
                <AttributeList>
                  <Culture>en-US</Culture>
                  <Text />
                </AttributeList>
              </MultilingualTextItem>
            </ObjectList>
          </MultilingualText>
          <MultilingualText ID="B" CompositionName="Title">
            <ObjectList>
              <MultilingualTextItem ID="C" CompositionName="Items">
                <AttributeList>
                  <Culture>en-US</Culture>
                  <Text>Close Clamps</Text>
                </AttributeList>
              </MultilingualTextItem>
            </ObjectList>
          </MultilingualText>
        </ObjectList>
      </SW.Blocks.CompileUnit>
      <SW.Blocks.CompileUnit ID="D" CompositionName="CompileUnits">
        <AttributeList>
          <NetworkSource><StructuredText xmlns="http://www.siemens.com/automation/Openness/SW/NetworkSource/StructuredText/v4">
  <Access Scope="LocalVariable" UId="21">
    <Symbol UId="22">
      <Component Name="Alarm_Clamp_Not_Close_Properly" UId="23" />
    </Symbol>
  </Access>
  <Token Text="." UId="24" />
  <Access Scope="Call" UId="25">
    <Instruction Name="TON" UId="26">
      <Token Text="(" UId="27" />
      <Parameter Name="IN" UId="28">
        <Token Text=":=" UId="29" />
        <Access Scope="LocalVariable" UId="30">
          <Symbol UId="31">
            <Component Name="MoveToWorkPos" UId="32" />
          </Symbol>
        </Access>
        <Blank UId="33" />
        <Token Text="=" UId="34" />
        <Blank UId="35" />
        <Access Scope="LiteralConstant" UId="36">
          <Constant UId="37">
            <ConstantValue UId="39">1</ConstantValue>
          </Constant>
        </Access>
        <Blank UId="40" />
        <Token Text="AND" UId="41" />
        <Blank UId="42" />
        <Token Text="(" UId="43" />
        <Access Scope="LocalVariable" UId="44">
          <Symbol UId="45">
            <Component Name="WorkPos1" UId="46" />
          </Symbol>
        </Access>
        <Blank UId="47" />
        <Token Text="=" UId="48" />
        <Blank UId="49" />
        <Access Scope="LiteralConstant" UId="50">
          <Constant UId="51">
            <ConstantValue UId="53">0</ConstantValue>
          </Constant>
        </Access>
        <Blank UId="54" />
        <Token Text="OR" UId="55" />
        <Blank UId="56" />
        <Access Scope="LocalVariable" UId="57">
          <Symbol UId="58">
            <Component Name="WorkPos2" UId="59" />
          </Symbol>
        </Access>
        <Blank UId="60" />
        <Token Text="=" UId="61" />
        <Blank UId="62" />
        <Access Scope="LiteralConstant" UId="63">
          <Constant UId="64">
            <ConstantValue UId="66">0</ConstantValue>
          </Constant>
        </Access>
        <Token Text=")" UId="67" />
      </Parameter>
      <Token Text="," UId="68" />
      <NewLine UId="69" />
      <Blank Num="36" UId="70" />
      <Parameter Name="PT" UId="71">
        <Token Text=":=" UId="72" />
        <Access Scope="TypedConstant" UId="73">
          <Constant UId="74">
            <ConstantValue UId="75">T#3s</ConstantValue>
          </Constant>
        </Access>
      </Parameter>
      <Token Text=")" UId="76" />
    </Instruction>
  </Access>
  <Token Text=";" UId="77" />
  <NewLine UId="78" />
  <Access Scope="LocalVariable" UId="79">
    <Symbol UId="80">
      <Component Name="Alarm_Clamp_Not_Open_Properly" UId="81" />
    </Symbol>
  </Access>
  <Token Text="." UId="82" />
  <Access Scope="Call" UId="83">
    <Instruction Name="TON" UId="84">
      <Token Text="(" UId="85" />
      <Parameter Name="IN" UId="86">
        <Token Text=":=" UId="87" />
        <Access Scope="LocalVariable" UId="88">
          <Symbol UId="89">
            <Component Name="MoveToBasePos" UId="90" />
          </Symbol>
        </Access>
        <Blank UId="91" />
        <Token Text="=" UId="92" />
        <Blank UId="93" />
        <Access Scope="LiteralConstant" UId="94">
          <Constant UId="95">
            <ConstantValue UId="97">1</ConstantValue>
          </Constant>
        </Access>
        <Blank UId="98" />
        <Token Text="AND" UId="99" />
        <Blank UId="100" />
        <Token Text="(" UId="101" />
        <Access Scope="LocalVariable" UId="102">
          <Symbol UId="103">
            <Component Name="BasePos1" UId="104" />
          </Symbol>
        </Access>
        <Blank UId="105" />
        <Token Text="=" UId="106" />
        <Blank UId="107" />
        <Access Scope="LiteralConstant" UId="108">
          <Constant UId="109">
            <ConstantValue UId="111">0</ConstantValue>
          </Constant>
        </Access>
        <Blank UId="112" />
        <Token Text="OR" UId="113" />
        <Blank UId="114" />
        <Access Scope="LocalVariable" UId="115">
          <Symbol UId="116">
            <Component Name="BasePos2" UId="117" />
          </Symbol>
        </Access>
        <Blank UId="118" />
        <Token Text="=" UId="119" />
        <Blank UId="120" />
        <Access Scope="LiteralConstant" UId="121">
          <Constant UId="122">
            <ConstantValue UId="124">0</ConstantValue>
          </Constant>
        </Access>
        <Token Text=")" UId="125" />
      </Parameter>
      <Blank UId="126" />
      <Token Text="," UId="127" />
      <NewLine UId="128" />
      <Blank Num="36" UId="129" />
      <Parameter Name="PT" UId="130">
        <Token Text=":=" UId="131" />
        <Access Scope="TypedConstant" UId="132">
          <Constant UId="133">
            <ConstantValue UId="134">T#3s</ConstantValue>
          </Constant>
        </Access>
      </Parameter>
      <Token Text=")" UId="135" />
    </Instruction>
  </Access>
  <Token Text=";" UId="136" />
</StructuredText></NetworkSource>
          <ProgrammingLanguage>SCL</ProgrammingLanguage>
        </AttributeList>
        <ObjectList>
          <MultilingualText ID="E" CompositionName="Comment">
            <ObjectList>
              <MultilingualTextItem ID="F" CompositionName="Items">
                <AttributeList>
                  <Culture>en-US</Culture>
                  <Text />
                </AttributeList>
              </MultilingualTextItem>
            </ObjectList>
          </MultilingualText>
          <MultilingualText ID="10" CompositionName="Title">
            <ObjectList>
              <MultilingualTextItem ID="11" CompositionName="Items">
                <AttributeList>
                  <Culture>en-US</Culture>
                  <Text>Alarm Clamps not in position</Text>
                </AttributeList>
              </MultilingualTextItem>
            </ObjectList>
          </MultilingualText>
        </ObjectList>
      </SW.Blocks.CompileUnit>
      <MultilingualText ID="12" CompositionName="Title">
        <ObjectList>
          <MultilingualTextItem ID="13" CompositionName="Items">
            <AttributeList>
              <Culture>en-US</Culture>
              <Text />
            </AttributeList>
          </MultilingualTextItem>
        </ObjectList>
      </MultilingualText>
    </ObjectList>
  </SW.Blocks.FB>
</Document>